cerc_hub-0.3.1.4.data/data/hub/requirements.txt
cerc_hub-0.3.1.4.data/data/hub/catalog_factories/greenery/ecore_greenery/greenerycatalog.ecore
cerc_hub-0.3.1.4.data/data/hub/catalog_factories/greenery/ecore_greenery/greenerycatalog_no_quantities.ecore
cerc_hub-0.3.1.4.data/data/hub/config/configuration.ini
cerc_hub-0.3.1.4.data/data/hub/data/construction/eilat_archetypes.json
cerc_hub-0.3.1.4.data/data/hub/data/construction/eilat_constructions.json
cerc_hub-0.3.1.4.data/data/hub/data/construction/nrcan_archetypes.json
cerc_hub-0.3.1.4.data/data/hub/data/construction/nrcan_constructions.json
cerc_hub-0.3.1.4.data/data/hub/data/construction/palma_archetypes.json
cerc_hub-0.3.1.4.data/data/hub/data/construction/palma_constructions.json
cerc_hub-0.3.1.4.data/data/hub/data/construction/us_archetypes.xml
cerc_hub-0.3.1.4.data/data/hub/data/construction/us_constructions.xml
cerc_hub-0.3.1.4.data/data/hub/data/costs/montreal_costs.xml
cerc_hub-0.3.1.4.data/data/hub/data/customized_imports/ashrae_archetypes.xml
cerc_hub-0.3.1.4.data/data/hub/data/energy_systems/montreal_custom_systems.xml
cerc_hub-0.3.1.4.data/data/hub/data/energy_systems/montreal_future_systems.xml
cerc_hub-0.3.1.4.data/data/hub/data/energy_systems/palma_systems.xml
cerc_hub-0.3.1.4.data/data/hub/data/energy_systems/heat_pumps/air_source.xlsx
cerc_hub-0.3.1.4.data/data/hub/data/energy_systems/heat_pumps/as_parallel.txt
cerc_hub-0.3.1.4.data/data/hub/data/energy_systems/heat_pumps/as_series.txt
cerc_hub-0.3.1.4.data/data/hub/data/energy_systems/heat_pumps/constants.yaml
cerc_hub-0.3.1.4.data/data/hub/data/energy_systems/heat_pumps/demand.txt
cerc_hub-0.3.1.4.data/data/hub/data/energy_systems/heat_pumps/w2w_parallel.txt
cerc_hub-0.3.1.4.data/data/hub/data/energy_systems/heat_pumps/w2w_series.txt
cerc_hub-0.3.1.4.data/data/hub/data/energy_systems/heat_pumps/water_to_water.xlsx
cerc_hub-0.3.1.4.data/data/hub/data/energy_systems/heat_pumps/wt_hourly3.txt
cerc_hub-0.3.1.4.dist-info/licenses/LICENSE.md
cerc_hub-0.3.1.4.dist-info/METADATA
cerc_hub-0.3.1.4.dist-info/WHEEL
cerc_hub-0.3.1.4.dist-info/top_level.txt
cerc_hub-0.3.1.4.dist-info/RECORD
