Metadata-Version: 2.4
Name: cerc-hub
Version: 0.3.1.4
Summary: CERC Hub consist of a set of classes (Central data model), importers and exporters to help researchers to create better and more sustainable cities
License: LGPL-2.1-or-later
Classifier: License :: OSI Approved :: GNU Library or Lesser General Public License (LGPL)
Classifier: Programming Language :: Python
Classifier: Programming Language :: Python :: 3
License-File: LICENSE.md
Requires-Dist: xmltodict
Requires-Dist: numpy
Requires-Dist: trimesh[all]
Requires-Dist: pyproj
Requires-Dist: pandas
Requires-Dist: requests
Requires-Dist: esoreader
Requires-Dist: geomeppy
Requires-Dist: PyWavefront
Requires-Dist: xlrd
Requires-Dist: openpyxl
Requires-Dist: networkx
Requires-Dist: parseidf==1.0.0
Requires-Dist: ply
Requires-Dist: scipy
Requires-Dist: PyYAML
Requires-Dist: pyecore==0.12.2
Requires-Dist: python-dotenv
Requires-Dist: SQLAlchemy
Requires-Dist: bcrypt==4.0.1
Requires-Dist: shapely
Requires-Dist: geopandas
Requires-Dist: triangle
Requires-Dist: psycopg2-binary
Requires-Dist: Pillow
Requires-Dist: pathlib
Requires-Dist: sqlalchemy_utils
Requires-Dist: build
Requires-Dist: markdown
Requires-Dist: setuptools
Dynamic: classifier
Dynamic: description
Dynamic: license
Dynamic: license-file
Dynamic: requires-dist
Dynamic: summary
